equipment/__init__.py
equipment/__main__.py
equipment/Command/AbstractCommand.py
equipment/Command/CompileCommand.py
equipment/Command/NewProjectCommand.py
equipment/Command/__init__.py
equipment/Database/SQLAlchemyFactory.py
equipment/Database/__init__.py
equipment/Log/AbstractLogger.py
equipment/Log/LoggerFactory.py
equipment/Log/NullLogger.py
equipment/Log/__init__.py
equipment/Queue/AbstractQueue.py
equipment/Queue/QueueFactory.py
equipment/Queue/RedisQueue.py
equipment/Queue/SyncQueue.py
equipment/Queue/__init__.py
equipment/Scheduler/AbstractScheduler.py
equipment/Scheduler/Scheduler.py
equipment/Scheduler/__init__.py
equipment/Storage/AbstractStorage.py
equipment/Storage/LocalStorage.py
equipment/Storage/S3Storage.py
equipment/Storage/StorageFactory.py
equipment/Storage/__init__.py
equipment-1.1.0.dist-info/licenses/LICENSE.txt
equipment-1.1.0.dist-info/METADATA
equipment-1.1.0.dist-info/WHEEL
equipment-1.1.0.dist-info/entry_points.txt
equipment-1.1.0.dist-info/top_level.txt
equipment-1.1.0.dist-info/RECORD
