Metadata-Version: 2.4
Name: equipment
Version: 1.1.0
Summary: The root of your next python project
Author-email: Roger Vilà <rogervila@me.com>
License: MIT License
Project-URL: Homepage, https://github.com/rogervila/equipment
Project-URL: Issues, https://github.com/rogervila/equipment/issues
Keywords: equipment,application scaffolding,scheduler,dependency injection,web
Classifier: Development Status :: 4 - Beta
Classifier: Intended Audience :: Developers
Classifier: Programming Language :: Python :: 3.13
Classifier: License :: OSI Approved :: MIT License
Classifier: Operating System :: OS Independent
Requires-Python: >=3.12
License-File: LICENSE.txt
Requires-Dist: boto3<2,>=1.30
Requires-Dist: boto3-stubs-lite[s3]<2,>=1.30
Requires-Dist: cachetools<6,>=5.3
Requires-Dist: click<9,>=8.1
Requires-Dist: dependency-injector<5,>=4.46
Requires-Dist: moto[s3]<6,>=5.0
Requires-Dist: mypy-boto3-s3<2,>=1.30
Requires-Dist: parent-import>=0.0.1
Requires-Dist: python-dotenv<2,>=1.0
Requires-Dist: python-json-logger<4,>=3.2
Requires-Dist: python_sqlite_log_handler<2,>=1.0
Requires-Dist: PyYAML<7,>=6.0
Requires-Dist: redis<6,>=5.2
Requires-Dist: requests<3,>=2.32
Requires-Dist: rq<3,>=1.16
Requires-Dist: schedule<2,>=1.2
Requires-Dist: sqlalchemy<3,>=2.0
Requires-Dist: build
Requires-Dist: setuptools
Requires-Dist: wheel
Requires-Dist: twine
Dynamic: license-file
